LICENSE
MANIFEST.in
README
setup.py
poppy_ergo/__init__.py
poppy_ergo/_version.py
poppy_ergo/poppy_ergo.py
poppy_ergo.egg-info/PKG-INFO
poppy_ergo.egg-info/SOURCES.txt
poppy_ergo.egg-info/dependency_links.txt
poppy_ergo.egg-info/not-zip-safe
poppy_ergo.egg-info/requires.txt
poppy_ergo.egg-info/top_level.txt
poppy_ergo/configuration/poppy_ergo.json