Metadata-Version: 1.0
Name: poppy-ergo
Version: 1.0rc2
Summary:  Poppy Ergo Software Library
Home-page: https://github.com/poppy-project/poppy-ergo
Author: Pierre Rouanet, Matthieu Lapeyre
Author-email: pierre.rouanet@gmail.com
License: GNU GENERAL PUBLIC LICENSE Version 3
Platform: UNKNOWN
